meta_machina/__init__.py
meta_machina/githf.py
meta_machina/machina.yaml
meta_machina-0.0.8.dist-info/LICENSE
meta_machina-0.0.8.dist-info/METADATA
meta_machina-0.0.8.dist-info/WHEEL
meta_machina-0.0.8.dist-info/top_level.txt
meta_machina-0.0.8.dist-info/RECORD
